delta/__init__.py
delta/base.py
delta/deep_eq.py
delta/html.py
delta/op.py
quill_delta-1.0.2.dist-info/LICENSE.txt
quill_delta-1.0.2.dist-info/WHEEL
quill_delta-1.0.2.dist-info/METADATA
quill_delta-1.0.2.dist-info/RECORD
