Metadata-Version: 2.1
Name: quill-delta
Version: 1.0.2
Summary: Python port of the quill.js delta library that enables operational transformation with aditional functionality for rendering html
Home-page: https://github.com/forgeworks/delta-py
License: MIT
Author: Brantley Harris
Author-email: brantley@forge.works
Requires-Python: >=3.6,<4.0
Classifier: Development Status :: 5 - Production/Stable
Classifier: Intended Audience :: Developers
Classifier: License :: OSI Approved :: MIT License
Classifier: Natural Language :: English
Classifier: Programming Language :: Python :: 3
Classifier: Programming Language :: Python :: 3.6
Classifier: Programming Language :: Python :: 3.7
Classifier: Programming Language :: Python :: 3.8
Classifier: Programming Language :: Python :: 3.9
Classifier: Topic :: Text Processing :: Markup
Provides-Extra: html
Requires-Dist: cssutils (>=1.0,<2.0); extra == "html"
Requires-Dist: diff-match-patch (>=20181111.0,<20181112.0)
Requires-Dist: lxml (>=4.3,<5.0); extra == "html"
Project-URL: Repository, https://github.com/forgeworks/delta-py
